acousondePy/MTRead.py
acousondePy/__init__.py
acousondePy/main.py
acousondePy/test.py
acousondePy/data/SBI00003.MT
acousondePy/data/SBJ00003.MT
acousondePy/data/SBK00003.MT
acousondePy/data/SBP00003.MT
acousondePy/data/SBS00006.MT
acousondePy/data/SBT00003.MT
acousondePy/data/SBX00003.MT
acousondePy/data/SBY00003.MT
acousondePy/data/SBZ00003.MT
acousondePy-0.15.dist-info/LICENSE.txt
acousondePy-0.15.dist-info/METADATA
acousondePy-0.15.dist-info/WHEEL
acousondePy-0.15.dist-info/top_level.txt
acousondePy-0.15.dist-info/RECORD
