Metadata-Version: 2.1
Name: acousondePy
Version: 0.15
Summary: Read and plot Acousonde MT files
Home-page: https://github.com/SvenGastauer/acousondePy
Author: Sven Gastauer
Author-email: sgastauer@ucsd.edu
License: MIT
Download-URL: https://github.com/user/acousondePy/archive/0.15.tar.gz
Keywords: Acousonde,Python,acoustics,oceanography
Platform: UNKNOWN
Classifier: Development Status :: 3 - Alpha
Classifier: Intended Audience :: Developers
Classifier: Topic :: Software Development :: Build Tools
Classifier: License :: OSI Approved :: MIT License
Classifier: Programming Language :: Python :: 3
Classifier: Programming Language :: Python :: 3.4
Classifier: Programming Language :: Python :: 3.5
Classifier: Programming Language :: Python :: 3.6
Requires-Dist: scipy
Requires-Dist: numpy
Requires-Dist: pandas
Requires-Dist: datetime
Requires-Dist: matplotlib
